[
  { "hanzi": "家", "pinyin": "jiā", "english": ["Home", "Family"], "level": 1, "difficulty": 1, "characters": ["家"] },
  { "hanzi": "学校", "pinyin": "xué xiào", "english": ["School"], "level": 1, "difficulty": 1, "characters": ["学","校"] },
  { "hanzi": "医院", "pinyin": "yī yuàn", "english": ["Hospital"], "level": 1, "difficulty": 1, "characters": ["医","院"] },
  { "hanzi": "商店", "pinyin": "shāng diàn", "english": ["Shop", "Store"], "level": 1, "difficulty": 1, "characters": ["商","店"] },
  { "hanzi": "饭店", "pinyin": "fàn diàn", "english": ["Restaurant", "Hotel"], "level": 1, "difficulty": 1, "characters": ["饭","店"] },
  { "hanzi": "上", "pinyin": "shàng", "english": ["Up", "Above"], "level": 1, "difficulty": 1, "characters": ["上"] },
  { "hanzi": "下", "pinyin": "xià", "english": ["Down", "Below"], "level": 1, "difficulty": 1, "characters": ["下"] },
  { "hanzi": "左", "pinyin": "zuǒ", "english": ["Left"], "level": 1, "difficulty": 1, "characters": ["左"] },
  { "hanzi": "右", "pinyin": "yòu", "english": ["Right"], "level": 1, "difficulty": 1, "characters": ["右"] },
  { "hanzi": "里", "pinyin": "lǐ", "english": ["Inside", "Within"], "level": 1, "difficulty": 1, "characters": ["里"] },
  { "hanzi": "前", "pinyin": "qián", "english": ["Front", "Before"], "level": 1, "difficulty": 1, "characters": ["前"] },
  { "hanzi": "后", "pinyin": "hòu", "english": ["Back", "After"], "level": 1, "difficulty": 1, "characters": ["后"] },
  { "hanzi": "这", "pinyin": "zhè", "english": ["This"], "level": 1, "difficulty": 1, "characters": ["这"] },
  { "hanzi": "那", "pinyin": "nà", "english": ["That"], "level": 1, "difficulty": 1, "characters": ["那"] },
  { "hanzi": "哪", "pinyin": "nǎ", "english": ["Which"], "level": 1, "difficulty": 1, "characters": ["哪"] },
  { "hanzi": "这里", "pinyin": "zhè lǐ", "english": ["Here"], "level": 1, "difficulty": 1, "characters": ["这","里"] },
  { "hanzi": "那里", "pinyin": "nà lǐ", "english": ["There"], "level": 1, "difficulty": 1, "characters": ["那","里"] },
  { "hanzi": "那边", "pinyin": "nà biān", "english": ["Over there"], "level": 1, "difficulty": 1, "characters": ["那","边"] },
  { "hanzi": "哪里", "pinyin": "nǎ lǐ", "english": ["Where"], "level": 1, "difficulty": 1, "characters": ["哪","里"] },
  { "hanzi": "公司", "pinyin": "gōng sī", "english": ["Company"], "level": 1, "difficulty": 2, "characters": ["公","司"] },
  { "hanzi": "车站", "pinyin": "chē zhàn", "english": ["Station"], "level": 1, "difficulty": 2, "characters": ["车","站"] },
  { "hanzi": "外", "pinyin": "wài", "english": ["Outside"], "level": 1, "difficulty": 2, "characters": ["外"] },
  { "hanzi": "图书馆", "pinyin": "tú shū guǎn", "english": ["Library"], "level": 1, "difficulty": 3, "characters": ["图","书","馆"] },
  { "hanzi": "公园", "pinyin": "gōng yuán", "english": ["Park"], "level": 1, "difficulty": 3, "characters": ["公","园"] },
  { "hanzi": "银行", "pinyin": "yín háng", "english": ["Bank"], "level": 1, "difficulty": 3, "characters": ["银","行"] }
]
